buginjectx/__init__.py
buginjectx/comparer.py
buginjectx/config.py
buginjectx/injector.py
buginjectx/main.py
BugInjectX-0.2.0.dist-info/LICENSE.md
BugInjectX-0.2.0.dist-info/METADATA
BugInjectX-0.2.0.dist-info/WHEEL
BugInjectX-0.2.0.dist-info/entry_points.txt
BugInjectX-0.2.0.dist-info/top_level.txt
BugInjectX-0.2.0.dist-info/RECORD
