Metadata-Version: 2.1
Name: BugInjectX
Version: 0.2.0
Summary: Automated vulnerability scanner for SQL Injection (SQLi), SSRF, and XSS.
Home-page: https://github.com/greynodesecurity/BugInjectX
Author: Z3r0 S3c
Author-email: z3r0s3c@greynodesecurity.com
License: MIT
Project-URL: Source Code, https://github.com/greynodesecurity/BugInjectX
Project-URL: Bug Tracker, https://github.com/greynodesecurity/BugInjectX/issues
Project-URL: Documentation, https://github.com/greynodesecurity/BugInjectX/wiki
Keywords: security,bug bounty,pentesting,SQLi,SSRF,XSS,infosec,hacking,penetration testing,web security,vulnerability scanning,ethical hacking,bug bounty automation,cybersecurity
Classifier: Development Status :: 4 - Beta
Classifier: Intended Audience :: Developers
Classifier: Intended Audience :: Information Technology
Classifier: Topic :: Security
Classifier: Topic :: Software Development :: Testing
Classifier: License :: OSI Approved :: MIT License
Classifier: Programming Language :: Python :: 3
Classifier: Programming Language :: Python :: 3.7
Classifier: Programming Language :: Python :: 3.8
Classifier: Programming Language :: Python :: 3.9
Classifier: Programming Language :: Python :: 3.10
Classifier: Programming Language :: Python :: 3.11
Classifier: Operating System :: OS Independent
Requires-Python: >=3
License-File: LICENSE.md
Requires-Dist: requests
Requires-Dist: aiohttp
Requires-Dist: colorama
Requires-Dist: beautifulsoup4
Requires-Dist: tqdm
Requires-Dist: asyncio
Requires-Dist: argparse
Requires-Dist: injector
Provides-Extra: dev
Requires-Dist: black; extra == "dev"
Requires-Dist: flake8; extra == "dev"
Requires-Dist: pytest; extra == "dev"
